{"cheat_bingbuhack_index.md":"dc1445bb","hack_resources_packetsniffer.md":"79aa1055","hack_resources_co-op_master.md":"54ef362d","index.md":"65c97e2f","hack_resources_json_teleport.md":"191af3a8","hack_resources_json_to_bpfc.md":"ce28c9f7","cheat_index.md":"4825c16b","hack_index.md":"ff8f8c63","cheat_image_index.md":"48d69c20","cheat_acrepi-gc_index.md":"472a2943","cheat_bkebi-gc_09_debug.md":"bf77ce3e","cheat_akebi-private_index.md":"4093f04e","cheat_akebi-gc_index.md":"f6cf9742","hack_resources_gm_handbook.md":"f9e144c8","cheat_bkebi-gc_04_esp.md":"845b8032","cheat_bkebi-gc_index.md":"66f7ba27","cheat_bkebi-gc_07_misc.md":"5ab29acf","cheat_bkebi-gc_update_1_1_0.md":"73122d1a","cheat_bkebi-gc_08_hotkeys.md":"459be2c5","two_index.md":"c44413d0","hack_resources_combineexcelconfigdata.md":"16e13cf9","cheat_bkebi-gc_06_settings.md":"27d4876e","cheat_bkebi-gc_10_more_guis.md":"c9622414","cheat_bkebi-gc_03_teleport.md":"05bdcf6c","cheat_bkebi-gc_01_player.md":"47955f2d","cheat_bkebi-gc_02_world.md":"5c95219f","cheat_bkebi-gc_05_visuals.md":"f4ba526f"}
